phablytics/__init__.py
phablytics/classes.py
phablytics/cli.py
phablytics/settings.py
phablytics/constants/__init__.py
phablytics/constants/general.py
phablytics/constants/phab.py
phablytics/constants/ui.py
phablytics/metrics/__init__.py
phablytics/metrics/constants.py
phablytics/metrics/metrics.py
phablytics/metrics/stats.py
phablytics/metrics/utils.py
phablytics/reports/__init__.py
phablytics/reports/base.py
phablytics/reports/constants.py
phablytics/reports/group_review_status.py
phablytics/reports/new_project_tasks.py
phablytics/reports/recent_tasks.py
phablytics/reports/revision_status.py
phablytics/reports/upcoming_tasks_due.py
phablytics/reports/urgent_and_overdue_project_tasks.py
phablytics/reports/utils.py
phablytics/repos/__init__.py
phablytics/repos/report_last_run.py
phablytics/segments/__init__.py
phablytics/segments/utils.py
phablytics/utils/__init__.py
phablytics/utils/db.py
phablytics/utils/dt.py
phablytics/utils/phab.py
phablytics/utils/strings.py
phablytics/web/__init__.py
phablytics/web/app.py
phablytics/web/constants.py
phablytics/web/server.py
phablytics/web/utils.py
phablytics/web/explore/__init__.py
phablytics/web/explore/views.py
phablytics/web/help/__init__.py
phablytics/web/help/views.py
phablytics/web/home/__init__.py
phablytics/web/home/views.py
phablytics/web/metrics/__init__.py
phablytics/web/metrics/forms.py
phablytics/web/metrics/views.py
phablytics/web/reports/__init__.py
phablytics/web/reports/utils.py
phablytics/web/reports/views.py
phablytics/web/static/style.css
phablytics/web/templates/404.html
phablytics/web/templates/base.html
phablytics/web/templates/help.html
phablytics/web/templates/index.html
phablytics/web/templates/explore/explore.html
phablytics/web/templates/fragments/breadcrumbs.html
phablytics/web/templates/fragments/footer.html
phablytics/web/templates/fragments/header.html
phablytics/web/templates/fragments/css/common.html
phablytics/web/templates/fragments/js/common.html
phablytics-3.5.0.dist-info/LICENSE.md
phablytics-3.5.0.dist-info/METADATA
phablytics-3.5.0.dist-info/WHEEL
phablytics-3.5.0.dist-info/entry_points.txt
phablytics-3.5.0.dist-info/top_level.txt
phablytics-3.5.0.dist-info/RECORD
