Metadata-Version: 2.1
Name: phablytics
Version: 3.5.0
Summary: Analytics, metrics, and reports for Phabricator (https://phacility.com/phabricator/).
Home-page: https://github.com/hacktoolkit/phablytics
Author: Hacktoolkit
Author-email: hello@hacktoolkit.com
License: MIT
Keywords: phabricator slack slack-bot git source-control code-reviews
Platform: UNKNOWN
Classifier: Development Status :: 3 - Alpha
Classifier: Intended Audience :: Developers
Classifier: Topic :: Text Processing :: General
Classifier: License :: OSI Approved :: MIT License
Classifier: Programming Language :: Python :: 3
Requires-Python: >=3.0
License-File: LICENSE.md
Requires-Dist: emoji (<0.7.0,>=0.6.0)
Requires-Dist: htk (>=2.1.0)
Requires-Dist: markdown (<4,>=3.2.2)
Requires-Dist: numpy (<2,>=1.22.0)
Requires-Dist: phabricator (>=0.9.1)
Provides-Extra: dev
Provides-Extra: test
Provides-Extra: web
Requires-Dist: Flask (<3.0,>=2.1.3) ; extra == 'web'
Requires-Dist: Flask-WTF (==1.0.*) ; extra == 'web'
Requires-Dist: WTForms (<2.4.0,>=2.3.3) ; extra == 'web'
